kane_pe/___init__.py
kane_pe/checks.py
kane_pe/materials.py
kane_pe/sections.py
kane_pe-0.1.0.dist-info/METADATA
kane_pe-0.1.0.dist-info/WHEEL
kane_pe-0.1.0.dist-info/top_level.txt
kane_pe-0.1.0.dist-info/RECORD
