Metadata-Version: 2.4
Name: kane_pe
Version: 0.1.0
Summary: Python library για ΚΑΝ.ΕΠΕ. (Κανονισμός Επεμβάσεων)
Author-email: Navrozidis Vasileios <vnavrozidis@hotmail.com>
License-Expression: MIT
Requires-Python: >=3.8
